osxNC/__init__.py
osxNC/osxNC.py
osxNC-1.0.2.dist-info/DESCRIPTION.rst
osxNC-1.0.2.dist-info/METADATA
osxNC-1.0.2.dist-info/RECORD
osxNC-1.0.2.dist-info/WHEEL
osxNC-1.0.2.dist-info/metadata.json
osxNC-1.0.2.dist-info/top_level.txt
