Metadata-Version: 2.0
Name: osxNC
Version: 1.0.2
Summary: Improved Python wrapper for Mac OS 10.12 Notification Center
Home-page: UNKNOWN
Author: Tyler Georgiadis
Author-email: tyler.j.georgiadis@gmail.com
License: MIT
Keywords: mac osx notification center wrapper
Platform: UNKNOWN
